pycql2/__init__.py
pycql2/cql2.lark
pycql2/cql2_pydantic.py
pycql2/cql2_transformer.py
pycql2/utils.py
pycql2-0.2.0.dist-info/LICENSE
pycql2-0.2.0.dist-info/METADATA
pycql2-0.2.0.dist-info/WHEEL
pycql2-0.2.0.dist-info/RECORD
